pymgflip/__init__.py
pymgflip/client.py
pymgflip/exceptions.py
pymgflip/models.py
pymgflip/py.typed
pymgflip-0.1.1.dist-info/METADATA
pymgflip-0.1.1.dist-info/WHEEL
pymgflip-0.1.1.dist-info/licenses/LICENSE
pymgflip-0.1.1.dist-info/RECORD
