Metadata-Version: 2.4
Name: pymgflip
Version: 0.1.1
Summary: A type-safe Python client for the Imgflip meme generation API
Project-URL: Homepage, https://github.com/joelgrus/pymgflip
Project-URL: Documentation, https://github.com/joelgrus/pymgflip#readme
Project-URL: Repository, https://github.com/joelgrus/pymgflip
Project-URL: Issues, https://github.com/joelgrus/pymgflip/issues
Author-email: Joel Grus <joelgrus@gmail.com>
License: MIT
License-File: LICENSE
Keywords: api,client,imgflip,meme,meme-generator
Classifier: Development Status :: 3 - Alpha
Classifier: Intended Audience :: Developers
Classifier: License :: OSI Approved :: MIT License
Classifier: Programming Language :: Python :: 3
Classifier: Programming Language :: Python :: 3.8
Classifier: Programming Language :: Python :: 3.9
Classifier: Programming Language :: Python :: 3.10
Classifier: Programming Language :: Python :: 3.11
Classifier: Programming Language :: Python :: 3.12
Classifier: Typing :: Typed
Requires-Python: >=3.8
Requires-Dist: httpx>=0.24.0
Requires-Dist: pydantic>=2.0.0
Requires-Dist: typing-extensions>=4.0.0; python_version < '3.10'
Provides-Extra: dev
Requires-Dist: black>=23.0.0; extra == 'dev'
Requires-Dist: mypy>=1.0.0; extra == 'dev'
Requires-Dist: pytest-asyncio>=0.21.0; extra == 'dev'
Requires-Dist: pytest-cov>=4.0.0; extra == 'dev'
Requires-Dist: pytest-httpx>=0.22.0; extra == 'dev'
Requires-Dist: pytest>=7.0.0; extra == 'dev'
Requires-Dist: ruff>=0.1.0; extra == 'dev'
